bazema_linker
