Metadata-Version: 2.1
Name: bazema-linker
Version: 1.2
Summary: Application building relations between drugs, scientific publications, pubmed, journals and clinical trials.
Home-page: UNKNOWN
Author: Baptiste Azéma
Author-email: baptiste@azema.tech
License: LICENSE
Platform: UNKNOWN
Requires-Python: ~=3.6
